{
  "crates/alcmy": "0.1.2",
  "crates/cgko": "0.1.2",
  "crates/cowp": "0.1.2",
  "crates/crv": "0.1.1",
  "crates/dllma": "0.1.2",
  "crates/dnapi": "0.1.1",
  "crates/dnsim": "0.1.1",
  "crates/ensof": "0.1.0",
  "crates/ethcli": "0.21.8",
  "crates/kybr": "0.1.2",
  "crates/lfi": "0.1.1",
  "crates/mrls": "0.1.2",
  "crates/oinch": "0.1.1",
  "crates/openoc": "0.1.1",
  "crates/pythc": "0.1.1",
  "crates/tndrly": "0.3.4",
  "crates/unswp": "0.1.1",
  "crates/vlra": "0.1.0",
  "crates/yldfi-common": "0.1.3",
  "crates/ykong": "0.1.1",
  "crates/zrxswap": "0.1.1"
}
